{"columns":[{"distinct_values":5,"name":"w_warehouse_sk","type":{"base":"int","nullable":false,"props":[32]}},{"distinct_values":5,"name":"w_warehouse_id","type":{"base":"string","nullable":false,"props":[]}},{"distinct_values":4,"name":"w_warehouse_name","type":{"base":"string","nullable":true,"props":[20]}},{"distinct_values":4,"name":"w_warehouse_sq_ft","type":{"base":"int","nullable":true,"props":[32]}},{"distinct_values":4,"name":"w_street_number","type":{"base":"string","nullable":true,"props":[]}},{"distinct_values":4,"name":"w_street_name","type":{"base":"string","nullable":true,"props":[60]}},{"distinct_values":4,"name":"w_street_type","type":{"base":"string","nullable":true,"props":[]}},{"distinct_values":4,"name":"w_suite_number","type":{"base":"string","nullable":true,"props":[]}},{"distinct_values":1,"name":"w_city","type":{"base":"string","nullable":true,"props":[60]}},{"distinct_values":1,"name":"w_county","type":{"base":"string","nullable":true,"props":[30]}},{"distinct_values":1,"name":"w_state","type":{"base":"char","nullable":true,"props":[2]}},{"distinct_values":1,"name":"w_zip","type":{"base":"string","nullable":true,"props":[]}},{"distinct_values":1,"name":"w_country","type":{"base":"string","nullable":true,"props":[20]}},{"distinct_values":1,"name":"w_gmt_offset","type":{"base":"decimal","nullable":true,"props":[5,2]}}],"indices":[{"columns":["w_warehouse_sk"],"name":"pk_hash","type":0}],"num_rows":5,"pkey":["w_warehouse_sk"]}